mdast-0.2.1.dist-info/METADATA
mdast-0.2.1.dist-info/WHEEL
mdast/__init__.py
mdast/mdast.abi3.so
mdast-0.2.1.dist-info/RECORD
