Metadata-Version: 2.4
Name: mdast
Version: 0.2.1
Requires-Dist: maturin[zig] ; extra == 'dev'
Requires-Dist: pip ; extra == 'dev'
Provides-Extra: dev
